boringauth/__init__.py
boringauth/cli.py
boringauth/presets/basic/create_db.py
boringauth/presets/basic/database.py
boringauth/presets/basic/models.py
boringauth/presets/basic/repository.py
boringauth/presets/basic/requirements.txt
boringauth/presets/basic/router.py
boringauth/presets/basic/schemas.py
boringauth/presets/basic/service.py
boringauth-0.1.1.dist-info/METADATA
boringauth-0.1.1.dist-info/WHEEL
boringauth-0.1.1.dist-info/entry_points.txt
boringauth-0.1.1.dist-info/RECORD
