Metadata-Version: 2.4
Name: boringauth
Version: 0.1.1
Summary: Boring, predictable FastAPI auth generator
Author-email: Feroz <feroz-chand@outlook.com>
License: MIT
Requires-Python: >=3.10
